MANIFEST.in
README.md
setup.py
ralbot/uvmgen/__about__.py
ralbot/uvmgen/__init__.py
ralbot/uvmgen/exporter.py
ralbot/uvmgen/typemaps.py
ralbot_uvm.egg-info/PKG-INFO
ralbot_uvm.egg-info/SOURCES.txt
ralbot_uvm.egg-info/dependency_links.txt
ralbot_uvm.egg-info/requires.txt
ralbot_uvm.egg-info/top_level.txt