Metadata-Version: 2.1
Name: ralbot-uvm
Version: 1.0.0
Summary: Generate UVM register model from compiled SystemRDL input
Home-page: https://github.com/zhajio1988/RALBot-uvm
Author: Jude Zhang
Author-email: 564193687@qq.com
License: UNKNOWN
Project-URL: Source, https://github.com/zhajio1988/RALBot-uvm
Project-URL: Tracker, https://github.com/zhajio1988/RALBot-uvm/issues
Platform: UNKNOWN
Classifier: Development Status :: 5 - Production/Stable
Classifier: Programming Language :: Python
Classifier: Programming Language :: Python :: 3
Classifier: Programming Language :: Python :: 3.4
Classifier: Programming Language :: Python :: 3.5
Classifier: Programming Language :: Python :: 3.6
Classifier: Programming Language :: Python :: 3.7
Classifier: Programming Language :: Python :: 3 :: Only
Classifier: Intended Audience :: Developers
Classifier: License :: OSI Approved :: GNU General Public License v3 (GPLv3)
Classifier: Operating System :: OS Independent
Classifier: Topic :: Scientific/Engineering :: Electronic Design Automation (EDA)
Requires-Python: >=3.4
